pyDataCube/EntryPoint.py
pyDataCube/Enums.py
pyDataCube/Interface.py
pyDataCube/__init__.py
pyDataCube/timers.py
pyDataCube/converter/__init__.py
pyDataCube/converter/export.py
pyDataCube/converter/importer.py
pyDataCube/converter/qb_integrity_constraints.py
pyDataCube/converter/validator.py
pyDataCube/cube/AggregateFunction.py
pyDataCube/cube/Attribute.py
pyDataCube/cube/Axis.py
pyDataCube/cube/BaseCube.py
pyDataCube/cube/BooleanConnective.py
pyDataCube/cube/Cube.py
pyDataCube/cube/CubeOperators.py
pyDataCube/cube/Cuboid.py
pyDataCube/cube/Dimension.py
pyDataCube/cube/Hierarchy.py
pyDataCube/cube/Level.py
pyDataCube/cube/LevelMember.py
pyDataCube/cube/LevelMemberType.py
pyDataCube/cube/Measure.py
pyDataCube/cube/NonTopLevel.py
pyDataCube/cube/Predicate.py
pyDataCube/cube/PredicateOperator.py
pyDataCube/cube/TopLevel.py
pyDataCube/cube/View.py
pyDataCube/cube/__init__.py
pyDataCube/engines/__init__.py
pyDataCube/engines/engine.py
pyDataCube/engines/postgres.py
pyDataCube/session/__init__.py
pyDataCube/session/cube_metadata.py
pyDataCube/session/infer_cube.py
pyDataCube/session/session.py
pyDataCube/session/sql_queries.py
pydatacube-0.1.7.dist-info/licenses/LICENSE
pydatacube-0.1.7.dist-info/METADATA
pydatacube-0.1.7.dist-info/WHEEL
pydatacube-0.1.7.dist-info/top_level.txt
pydatacube-0.1.7.dist-info/RECORD
