Metadata-Version: 2.4
Name: pydatacube
Version: 0.1.7
Summary: Querying data cubes with Python using MDX inspired declarative syntax
Author-email: Sigmundur Vang <siva@cs.aau.dk>
License-Expression: Unlicense
Project-URL: Homepage, https://gitlab.com/sigmundur_phd/pycube
Project-URL: Source, https://gitlab.com/sigmundur_phd/pycube.git
Classifier: Programming Language :: Python :: 3
Classifier: Operating System :: OS Independent
Requires-Python: >=3.8
License-File: LICENSE
Requires-Dist: numpy
Requires-Dist: psycopg2
Requires-Dist: pandas
Requires-Dist: levenshtein
Requires-Dist: rdflib
Requires-Dist: sqlalchemy
Dynamic: license-file
